aiaio/__init__.py
aiaio/db.py
aiaio/logging.py
aiaio/prompts.py
aiaio/app/__init__.py
aiaio/app/app.py
aiaio/app/static/script.js
aiaio/app/templates/index.html
aiaio/cli/__init__.py
aiaio/cli/aiaio.py
aiaio/cli/run_app.py
aiaio-0.0.9.dist-info/licenses/LICENSE
aiaio-0.0.9.dist-info/METADATA
aiaio-0.0.9.dist-info/WHEEL
aiaio-0.0.9.dist-info/entry_points.txt
aiaio-0.0.9.dist-info/top_level.txt
aiaio-0.0.9.dist-info/RECORD
