Metadata-Version: 2.4
Name: aiaio
Version: 0.0.9
Summary: aiaio
Author: abhishek
Project-URL: Homepage, https://github.com/abhishekkrthakur/aiaio
Project-URL: Issues, https://github.com/abhishekkrthakur/aiaio/issues
Keywords: aiaio
Classifier: Development Status :: 5 - Production/Stable
Classifier: License :: OSI Approved :: Apache Software License
Classifier: Operating System :: OS Independent
Classifier: Programming Language :: Python :: 3.10
Classifier: Programming Language :: Python :: 3.11
Classifier: Topic :: Scientific/Engineering :: Artificial Intelligence
License-File: LICENSE
Requires-Dist: fastapi
Requires-Dist: uvicorn
Requires-Dist: loguru
Requires-Dist: jinja2
Requires-Dist: python-multipart
Requires-Dist: openai
Requires-Dist: websockets
Dynamic: license-file
